examples/mlx90640_demo.py
mlx9064x_visualizer-1.1.3.dist-info/LICENSE
mlx9064x_visualizer-1.1.3.dist-info/METADATA
mlx9064x_visualizer-1.1.3.dist-info/NOTICE
mlx9064x_visualizer-1.1.3.dist-info/WHEEL
mlx9064x_visualizer-1.1.3.dist-info/entry_points.txt
mlx9064x_visualizer-1.1.3.dist-info/top_level.txt
mlx9064x_visualizer-1.1.3.dist-info/RECORD
